LICENSE
MANIFEST.in
README.md
requirements.txt
setup.cfg
setup.py
minerl/__init__.py
minerl/Malmo/Minecraft/CMakeLists.txt
minerl/Malmo/Minecraft/CREDITS-fml.txt
minerl/Malmo/Minecraft/LICENSE-new.txt
minerl/Malmo/Minecraft/Minecraft.iml
minerl/Malmo/Minecraft/Minecraft.ipr
minerl/Malmo/Minecraft/Minecraft.iws
minerl/Malmo/Minecraft/MinecraftForge-Credits.txt
minerl/Malmo/Minecraft/Paulscode IBXM Library License.txt
minerl/Malmo/Minecraft/Paulscode SoundSystem CodecIBXM License.txt
minerl/Malmo/Minecraft/README.txt
minerl/Malmo/Minecraft/build.gradle
minerl/Malmo/Minecraft/gradlew
minerl/Malmo/Minecraft/gradlew.bat
minerl/Malmo/Minecraft/launchClient.bat
minerl/Malmo/Minecraft/launchClient.sh
minerl/Malmo/Minecraft/launch_minecraft_in_background.py
minerl/Malmo/Minecraft/wait_for_port.sh
minerl/Malmo/Minecraft/.idea/modules/Malmo.iml
minerl/Malmo/Minecraft/gradle/wrapper/gradle-wrapper.jar
minerl/Malmo/Minecraft/gradle/wrapper/gradle-wrapper.properties
minerl/Malmo/Minecraft/run/options.txt
minerl/Malmo/Minecraft/run/config/forge.cfg
minerl/Malmo/Minecraft/run/config/forgeChunkLoading.cfg
minerl/Malmo/Minecraft/run/config/malmomodCLIENTPermanent.cfg
minerl/Malmo/Minecraft/shared_configs/Attach on 1044.run.xml
minerl/Malmo/Minecraft/shared_configs/Interactive + Auto-debugger.run.xml
minerl/Malmo/Minecraft/shared_configs/Wait For Port.run.xml
minerl/Malmo/Minecraft/shared_configs/interactive.py.run.xml
minerl/Malmo/Minecraft/src/main/java/com/microsoft/Malmo/EpisodeEventWrapper.java
minerl/Malmo/Minecraft/src/main/java/com/microsoft/Malmo/IState.java
minerl/Malmo/Minecraft/src/main/java/com/microsoft/Malmo/MalmoMod.java
minerl/Malmo/Minecraft/src/main/java/com/microsoft/Malmo/MalmoModGuiOptions.java
minerl/Malmo/Minecraft/src/main/java/com/microsoft/Malmo/MixinTextureHandler.java
minerl/Malmo/Minecraft/src/main/java/com/microsoft/Malmo/OverclockingClassTransformer.java
minerl/Malmo/Minecraft/src/main/java/com/microsoft/Malmo/OverclockingPlugin.java
minerl_shwang.egg-info/PKG-INFO
minerl_shwang.egg-info/SOURCES.txt
minerl_shwang.egg-info/dependency_links.txt
minerl_shwang.egg-info/requires.txt
minerl_shwang.egg-info/top_level.txt