Metadata-Version: 2.1
Name: minerl-shwang
Version: 0.4.2a0
Summary: MineRL environment and data loader for reinforcement learning from human demonstration in Minecraft
Home-page: http://github.com/minerllabs/minerl
Author: MineRL Labs
Author-email: minerl@andrew.cmu.edu
License: MIT
Platform: UNKNOWN
Classifier: Programming Language :: Python :: 3
Classifier: Operating System :: OS Independent
